{
  "$schema": "https://json-schema.org/draft/2020-12/schema",
  "$id": "https://raw.githubusercontent.com/api-evangelist/censys/refs/heads/main/json-schema/platform-whoisupdated-schema.json",
  "title": "WhoisUpdated",
  "description": "WhoisUpdated schema from Censys Platform API",
  "type": "object",
  "properties": {
    "diff": {
      "additionalProperties": {
        "$ref": "#/components/schemas/FieldDiff"
      },
      "type": "object"
    },
    "whois": {
      "$ref": "#/components/schemas/Whois"
    }
  },
  "additionalProperties": false
}